README.txt
setup.py
sinknal/__init__.py
sinknal/loop.py
sinknal.egg-info/PKG-INFO
sinknal.egg-info/SOURCES.txt
sinknal.egg-info/dependency_links.txt
sinknal.egg-info/top_level.txt