Metadata-Version: 1.0
Name: sinknal
Version: 0.1a0
Summary: Rsync caller coordinator
Home-page: https://github.com/gamikun/sinknal
Author: Gamaliel Espinoza M.
Author-email: gamaliel.espinoza@gmail.com
License: UNKNOWN
Keywords: rsync,coordinator,daemon
Platform: UNKNOWN
